SG23001UNO/__init__.py
SG23001UNO/bisection.py
SG23001UNO/cramer.py
SG23001UNO/gauss.py
SG23001UNO/gauss_jordan.py
SG23001UNO/gauss_seidel.py
SG23001UNO/jacobi.py
SG23001UNO/lu.py
sg23001uno-0.1.1.dist-info/METADATA
sg23001uno-0.1.1.dist-info/WHEEL
sg23001uno-0.1.1.dist-info/top_level.txt
sg23001uno-0.1.1.dist-info/RECORD
