Metadata-Version: 2.4
Name: SG23001UNO
Version: 0.1.1
Summary: Librería sencilla para resolver sistemas de ecuaciones lineales y no lineales
Author: Luis Eduardo Salamanca Garcia
License: MIT
Dynamic: author
Dynamic: description
Dynamic: description-content-type
Dynamic: license
Dynamic: summary
